{
  "results": [
    {
      "command": "./main < ./data/ladrilho_2_1.txt",
      "mean": 0.005284637466666668,
      "stddev": 0.00039100152000002934,
      "median": 0.005253415799999999,
      "user": 0.0030223799999999994,
      "system": 0.0022345266666666678,
      "min": 0.004910182800000001,
      "max": 0.005690313800000001,
      "times": [
        0.004910182800000001,
        0.005253415799999999,
        0.005690313800000001
      ],
      "exit_codes": [
        0,
        0,
        0
      ],
      "parameters": {
        "step": "1"
      }
    },
    {
      "command": "./main < ./data/ladrilho_2_2.txt",
      "mean": 0.004774585799999999,
      "stddev": 0.0005065860935053391,
      "median": 0.005007174799999998,
      "user": 0.0022117133333333316,
      "system": 0.0028415733333333336,
      "min": 0.004193472799999999,
      "max": 0.005123109799999999,
      "times": [
        0.005123109799999999,
        0.005007174799999998,
        0.004193472799999999
      ],
      "exit_codes": [
        0,
        0,
        0
      ],
      "parameters": {
        "step": "2"
      }
    },
    {
      "command": "./main < ./data/ladrilho_2_3.txt",
      "mean": 0.005348850133333333,
      "stddev": 0.0003716769929472809,
      "median": 0.005504747799999999,
      "user": 0.0018357133333333324,
      "system": 0.003539193333333334,
      "min": 0.0049246128,
      "max": 0.0056171898,
      "times": [
        0.005504747799999999,
        0.0049246128,
        0.0056171898
      ],
      "exit_codes": [
        0,
        0,
        0
      ],
      "parameters": {
        "step": "3"
      }
    },
    {
      "command": "./main < ./data/ladrilho_2_4.txt",
      "mean": 0.004522281133333333,
      "stddev": 0.0008748112767679278,
      "median": 0.0047101747999999995,
      "user": 0.001697713333333332,
      "system": 0.003049193333333334,
      "min": 0.0035687897999999996,
      "max": 0.005287878799999998,
      "times": [
        0.005287878799999998,
        0.0047101747999999995,
        0.0035687897999999996
      ],
      "exit_codes": [
        0,
        0,
        0
      ],
      "parameters": {
        "step": "4"
      }
    },
    {
      "command": "./main < ./data/ladrilho_2_5.txt",
      "mean": 0.0052952394666666664,
      "stddev": 0.0015158472382220233,
      "median": 0.0052421568,
      "user": 0.0023599199999999993,
      "system": 0.0027185733333333338,
      "min": 0.0038066307999999986,
      "max": 0.0068369308,
      "times": [
        0.0052421568,
        0.0038066307999999986,
        0.0068369308
      ],
      "exit_codes": [
        0,
        0,
        0
      ],
      "parameters": {
        "step": "5"
      }
    },
    {
      "command": "./main < ./data/ladrilho_2_6.txt",
      "mean": 0.005888255466666666,
      "stddev": 0.001219517962955991,
      "median": 0.005456043799999999,
      "user": 0.0014749199999999991,
      "system": 0.0045915266666666675,
      "min": 0.004943706800000001,
      "max": 0.007265015799999998,
      "times": [
        0.004943706800000001,
        0.007265015799999998,
        0.005456043799999999
      ],
      "exit_codes": [
        0,
        0,
        0
      ],
      "parameters": {
        "step": "6"
      }
    },
    {
      "command": "./main < ./data/ladrilho_2_7.txt",
      "mean": 0.005787131133333334,
      "stddev": 0.001125675255071965,
      "median": 0.005411511799999999,
      "user": 0.0007449199999999993,
      "system": 0.005048526666666667,
      "min": 0.0048972918,
      "max": 0.0070525898,
      "times": [
        0.0070525898,
        0.0048972918,
        0.005411511799999999
      ],
      "exit_codes": [
        0,
        0,
        0
      ],
      "parameters": {
        "step": "7"
      }
    },
    {
      "command": "./main < ./data/ladrilho_2_8.txt",
      "mean": 0.006200522466666666,
      "stddev": 0.0015021941945119264,
      "median": 0.005448189800000001,
      "user": 0.002143713333333332,
      "system": 0.0038858600000000014,
      "min": 0.005223143799999998,
      "max": 0.0079302338,
      "times": [
        0.005448189800000001,
        0.0079302338,
        0.005223143799999998
      ],
      "exit_codes": [
        0,
        0,
        0
      ],
      "parameters": {
        "step": "8"
      }
    },
    {
      "command": "./main < ./data/ladrilho_2_9.txt",
      "mean": 0.0045908248,
      "stddev": 0.0003930000674974502,
      "median": 0.0047856138,
      "user": 0.0030960466666666657,
      "system": 0.0017498600000000009,
      "min": 0.004138476799999999,
      "max": 0.0048483838,
      "times": [
        0.0047856138,
        0.004138476799999999,
        0.0048483838
      ],
      "exit_codes": [
        0,
        0,
        0
      ],
      "parameters": {
        "step": "9"
      }
    },
    {
      "command": "./main < ./data/ladrilho_2_10.txt",
      "mean": 0.0055924908,
      "stddev": 0.0006341768182667983,
      "median": 0.005445492799999998,
      "user": 0.0032520466666666656,
      "system": 0.002316526666666668,
      "min": 0.0050447218000000005,
      "max": 0.0062872577999999995,
      "times": [
        0.0050447218000000005,
        0.0062872577999999995,
        0.005445492799999998
      ],
      "exit_codes": [
        0,
        0,
        0
      ],
      "parameters": {
        "step": "10"
      }
    },
    {
      "command": "./main < ./data/ladrilho_2_11.txt",
      "mean": 0.006443636466666666,
      "stddev": 0.0008563468665805549,
      "median": 0.0066988468,
      "user": 0.0019169199999999993,
      "system": 0.004253526666666668,
      "min": 0.005488697799999999,
      "max": 0.007143364800000001,
      "times": [
        0.005488697799999999,
        0.0066988468,
        0.007143364800000001
      ],
      "exit_codes": [
        0,
        0,
        0
      ],
      "parameters": {
        "step": "11"
      }
    },
    {
      "command": "./main < ./data/ladrilho_2_12.txt",
      "mean": 0.005339272466666665,
      "stddev": 0.0003823440397042089,
      "median": 0.0055091438,
      "user": 0.0038450466666666654,
      "system": 0.0017515733333333336,
      "min": 0.004901427799999998,
      "max": 0.005607245799999999,
      "times": [
        0.0055091438,
        0.005607245799999999,
        0.004901427799999998
      ],
      "exit_codes": [
        0,
        0,
        0
      ],
      "parameters": {
        "step": "12"
      }
    },
    {
      "command": "./main < ./data/ladrilho_2_13.txt",
      "mean": 0.005290359799999998,
      "stddev": 0.0018297267316659612,
      "median": 0.004399603799999999,
      "user": 0.001449046666666666,
      "system": 0.0029998600000000013,
      "min": 0.004076576799999999,
      "max": 0.007394898799999999,
      "times": [
        0.004399603799999999,
        0.004076576799999999,
        0.007394898799999999
      ],
      "exit_codes": [
        0,
        0,
        0
      ],
      "parameters": {
        "step": "13"
      }
    },
    {
      "command": "./main < ./data/ladrilho_2_14.txt",
      "mean": 0.0088294798,
      "stddev": 0.0018879271905100053,
      "median": 0.0095310668,
      "user": 0.0031172533333333322,
      "system": 0.005379193333333335,
      "min": 0.006691201799999999,
      "max": 0.0102661708,
      "times": [
        0.006691201799999999,
        0.0102661708,
        0.0095310668
      ],
      "exit_codes": [
        0,
        0,
        0
      ],
      "parameters": {
        "step": "14"
      }
    },
    {
      "command": "./main < ./data/ladrilho_2_15.txt",
      "mean": 0.007281075133333333,
      "stddev": 0.0017349305013865336,
      "median": 0.006745747799999998,
      "user": 0.0036380466666666653,
      "system": 0.003233526666666668,
      "min": 0.005876897800000001,
      "max": 0.009220579799999998,
      "times": [
        0.009220579799999998,
        0.005876897800000001,
        0.006745747799999998
      ],
      "exit_codes": [
        0,
        0,
        0
      ],
      "parameters": {
        "step": "15"
      }
    },
    {
      "command": "./main < ./data/ladrilho_2_16.txt",
      "mean": 0.009828035466666668,
      "stddev": 0.0015129790799803973,
      "median": 0.0101145938,
      "user": 0.004158379999999999,
      "system": 0.0045851933333333345,
      "min": 0.008192268800000001,
      "max": 0.011177243799999998,
      "times": [
        0.0101145938,
        0.011177243799999998,
        0.008192268800000001
      ],
      "exit_codes": [
        0,
        0,
        0
      ],
      "parameters": {
        "step": "16"
      }
    },
    {
      "command": "./main < ./data/ladrilho_2_17.txt",
      "mean": 0.008989935466666666,
      "stddev": 0.0013785611686357399,
      "median": 0.0095995728,
      "user": 0.002543046666666665,
      "system": 0.005922860000000001,
      "min": 0.0074116617999999985,
      "max": 0.009958571800000001,
      "times": [
        0.0074116617999999985,
        0.0095995728,
        0.009958571800000001
      ],
      "exit_codes": [
        0,
        0,
        0
      ],
      "parameters": {
        "step": "17"
      }
    },
    {
      "command": "./main < ./data/ladrilho_2_18.txt",
      "mean": 0.009482982133333333,
      "stddev": 0.0003550166246337395,
      "median": 0.009500057800000001,
      "user": 0.005710713333333332,
      "system": 0.0032465266666666676,
      "min": 0.009119735799999999,
      "max": 0.0098291528,
      "times": [
        0.009119735799999999,
        0.009500057800000001,
        0.0098291528
      ],
      "exit_codes": [
        0,
        0,
        0
      ],
      "parameters": {
        "step": "18"
      }
    },
    {
      "command": "./main < ./data/ladrilho_2_19.txt",
      "mean": 0.007072210466666666,
      "stddev": 0.0033885994326146507,
      "median": 0.0052274048,
      "user": 0.002685713333333331,
      "system": 0.003788526666666668,
      "min": 0.0050062818,
      "max": 0.0109829448,
      "times": [
        0.0109829448,
        0.0052274048,
        0.0050062818
      ],
      "exit_codes": [
        0,
        0,
        0
      ],
      "parameters": {
        "step": "19"
      }
    },
    {
      "command": "./main < ./data/ladrilho_2_20.txt",
      "mean": 0.004980075466666667,
      "stddev": 0.0013118014684441906,
      "median": 0.005515363800000001,
      "user": 0.0016662533333333326,
      "system": 0.0033715266666666673,
      "min": 0.003485270799999999,
      "max": 0.0059395917999999995,
      "times": [
        0.003485270799999999,
        0.0059395917999999995,
        0.005515363800000001
      ],
      "exit_codes": [
        0,
        0,
        0
      ],
      "parameters": {
        "step": "20"
      }
    },
    {
      "command": "./main < ./data/ladrilho_2_21.txt",
      "mean": 0.0057810558,
      "stddev": 0.0013666152084024967,
      "median": 0.0054548888,
      "user": 0.002338713333333332,
      "system": 0.0030545266666666677,
      "min": 0.004607034799999998,
      "max": 0.007281243799999998,
      "times": [
        0.007281243799999998,
        0.004607034799999998,
        0.0054548888
      ],
      "exit_codes": [
        0,
        0,
        0
      ],
      "parameters": {
        "step": "21"
      }
    },
    {
      "command": "./main < ./data/ladrilho_2_22.txt",
      "mean": 0.005744452133333332,
      "stddev": 0.0006531466999766077,
      "median": 0.0058998178,
      "user": 0.002002713333333332,
      "system": 0.0035288600000000013,
      "min": 0.0050276318,
      "max": 0.0063059067999999985,
      "times": [
        0.0058998178,
        0.0050276318,
        0.0063059067999999985
      ],
      "exit_codes": [
        0,
        0,
        0
      ],
      "parameters": {
        "step": "22"
      }
    },
    {
      "command": "./main < ./data/ladrilho_2_23.txt",
      "mean": 0.005328383466666667,
      "stddev": 0.0009200178876643294,
      "median": 0.005339556800000001,
      "user": 0.0025913799999999995,
      "system": 0.002561526666666668,
      "min": 0.004402829799999999,
      "max": 0.0062427638,
      "times": [
        0.005339556800000001,
        0.004402829799999999,
        0.0062427638
      ],
      "exit_codes": [
        0,
        0,
        0
      ],
      "parameters": {
        "step": "23"
      }
    },
    {
      "command": "./main < ./data/ladrilho_2_24.txt",
      "mean": 0.0074988168,
      "stddev": 0.0011290999658458065,
      "median": 0.007950408800000001,
      "user": 0.004017379999999998,
      "system": 0.0031775266666666676,
      "min": 0.0062138157999999995,
      "max": 0.0083322258,
      "times": [
        0.007950408800000001,
        0.0062138157999999995,
        0.0083322258
      ],
      "exit_codes": [
        0,
        0,
        0
      ],
      "parameters": {
        "step": "24"
      }
    },
    {
      "command": "./main < ./data/ladrilho_2_25.txt",
      "mean": 0.012146036466666668,
      "stddev": 0.0009712686727910723,
      "median": 0.0123674658,
      "user": 0.004956713333333332,
      "system": 0.004222526666666667,
      "min": 0.011083171800000001,
      "max": 0.012987471799999999,
      "times": [
        0.011083171800000001,
        0.012987471799999999,
        0.0123674658
      ],
      "exit_codes": [
        0,
        0,
        0
      ],
      "parameters": {
        "step": "25"
      }
    },
    {
      "command": "./main < ./data/ladrilho_2_26.txt",
      "mean": 0.011419423133333334,
      "stddev": 0.0010907427972323878,
      "median": 0.0110620808,
      "user": 0.005065379999999999,
      "system": 0.004507526666666668,
      "min": 0.0105521738,
      "max": 0.0126440148,
      "times": [
        0.0126440148,
        0.0110620808,
        0.0105521738
      ],
      "exit_codes": [
        0,
        0,
        0
      ],
      "parameters": {
        "step": "26"
      }
    },
    {
      "command": "./main < ./data/ladrilho_2_27.txt",
      "mean": 0.009550828466666666,
      "stddev": 0.0017968030391248614,
      "median": 0.0094426168,
      "user": 0.0051423799999999985,
      "system": 0.0039055266666666675,
      "min": 0.007810576799999998,
      "max": 0.011399291800000001,
      "times": [
        0.011399291800000001,
        0.007810576799999998,
        0.0094426168
      ],
      "exit_codes": [
        0,
        0,
        0
      ],
      "parameters": {
        "step": "27"
      }
    },
    {
      "command": "./main < ./data/ladrilho_2_28.txt",
      "mean": 0.010761766133333335,
      "stddev": 0.004230073185841157,
      "median": 0.012682019800000001,
      "user": 0.005513046666666666,
      "system": 0.003991526666666668,
      "min": 0.005912167799999998,
      "max": 0.013691110800000001,
      "times": [
        0.013691110800000001,
        0.012682019800000001,
        0.005912167799999998
      ],
      "exit_codes": [
        0,
        0,
        0
      ],
      "parameters": {
        "step": "28"
      }
    },
    {
      "command": "./main < ./data/ladrilho_2_29.txt",
      "mean": 0.007901749466666665,
      "stddev": 0.0013736469715419375,
      "median": 0.007218939799999999,
      "user": 0.002011713333333332,
      "system": 0.0050815266666666675,
      "min": 0.0070033017999999985,
      "max": 0.0094830068,
      "times": [
        0.007218939799999999,
        0.0094830068,
        0.0070033017999999985
      ],
      "exit_codes": [
        0,
        0,
        0
      ],
      "parameters": {
        "step": "29"
      }
    },
    {
      "command": "./main < ./data/ladrilho_2_30.txt",
      "mean": 0.006565298133333332,
      "stddev": 0.0003410153937659308,
      "median": 0.006571206799999998,
      "user": 0.002480379999999999,
      "system": 0.0034711933333333345,
      "min": 0.006221366800000001,
      "max": 0.0069033207999999995,
      "times": [
        0.006571206799999998,
        0.0069033207999999995,
        0.006221366800000001
      ],
      "exit_codes": [
        0,
        0,
        0
      ],
      "parameters": {
        "step": "30"
      }
    },
    {
      "command": "./main < ./data/ladrilho_2_31.txt",
      "mean": 0.010598932466666667,
      "stddev": 0.0002679514628367104,
      "median": 0.0104611718,
      "user": 0.004518046666666665,
      "system": 0.0044421933333333346,
      "min": 0.0104278868,
      "max": 0.010907738799999999,
      "times": [
        0.0104278868,
        0.010907738799999999,
        0.0104611718
      ],
      "exit_codes": [
        0,
        0,
        0
      ],
      "parameters": {
        "step": "31"
      }
    },
    {
      "command": "./main < ./data/ladrilho_2_32.txt",
      "mean": 0.011933396133333335,
      "stddev": 0.003155687594626619,
      "median": 0.010327005799999999,
      "user": 0.004828046666666665,
      "system": 0.006300860000000001,
      "min": 0.0099041018,
      "max": 0.015569080800000001,
      "times": [
        0.0099041018,
        0.015569080800000001,
        0.010327005799999999
      ],
      "exit_codes": [
        0,
        0,
        0
      ],
      "parameters": {
        "step": "32"
      }
    },
    {
      "command": "./main < ./data/ladrilho_2_33.txt",
      "mean": 0.0117019738,
      "stddev": 0.002228828644188018,
      "median": 0.0128839528,
      "user": 0.006477713333333332,
      "system": 0.004188526666666667,
      "min": 0.0091311178,
      "max": 0.0130908508,
      "times": [
        0.0128839528,
        0.0130908508,
        0.0091311178
      ],
      "exit_codes": [
        0,
        0,
        0
      ],
      "parameters": {
        "step": "33"
      }
    },
    {
      "command": "./main < ./data/ladrilho_2_34.txt",
      "mean": 0.009523459133333334,
      "stddev": 0.001775660592176707,
      "median": 0.009031601799999999,
      "user": 0.005137713333333332,
      "system": 0.004533193333333334,
      "min": 0.008045575800000001,
      "max": 0.011493199800000001,
      "times": [
        0.009031601799999999,
        0.011493199800000001,
        0.008045575800000001
      ],
      "exit_codes": [
        0,
        0,
        0
      ],
      "parameters": {
        "step": "34"
      }
    },
    {
      "command": "./main < ./data/ladrilho_2_35.txt",
      "mean": 0.009860238133333333,
      "stddev": 0.0014222463646613173,
      "median": 0.0102817998,
      "user": 0.0027937133333333316,
      "system": 0.00653586,
      "min": 0.0082748668,
      "max": 0.0110240478,
      "times": [
        0.0102817998,
        0.0110240478,
        0.0082748668
      ],
      "exit_codes": [
        0,
        0,
        0
      ],
      "parameters": {
        "step": "35"
      }
    },
    {
      "command": "./main < ./data/ladrilho_2_36.txt",
      "mean": 0.0086316508,
      "stddev": 0.0013005185656464104,
      "median": 0.0081591368,
      "user": 0.0037737133333333324,
      "system": 0.0044421933333333346,
      "min": 0.007633445800000001,
      "max": 0.010102369799999998,
      "times": [
        0.010102369799999998,
        0.007633445800000001,
        0.0081591368
      ],
      "exit_codes": [
        0,
        0,
        0
      ],
      "parameters": {
        "step": "36"
      }
    },
    {
      "command": "./main < ./data/ladrilho_2_37.txt",
      "mean": 0.0053986854666666665,
      "stddev": 0.0012985282961203947,
      "median": 0.004663720799999998,
      "user": 0.0006545866666666659,
      "system": 0.005285860000000001,
      "min": 0.004634334799999999,
      "max": 0.0068980008,
      "times": [
        0.004663720799999998,
        0.0068980008,
        0.004634334799999999
      ],
      "exit_codes": [
        0,
        0,
        0
      ],
      "parameters": {
        "step": "37"
      }
    },
    {
      "command": "./main < ./data/ladrilho_2_38.txt",
      "mean": 0.0072915148,
      "stddev": 0.001587921985805034,
      "median": 0.007179413800000001,
      "user": 0.0037593799999999984,
      "system": 0.0033855266666666674,
      "min": 0.005762613799999998,
      "max": 0.0089325168,
      "times": [
        0.005762613799999998,
        0.0089325168,
        0.007179413800000001
      ],
      "exit_codes": [
        0,
        0,
        0
      ],
      "parameters": {
        "step": "38"
      }
    },
    {
      "command": "./main < ./data/ladrilho_2_39.txt",
      "mean": 0.008826156466666667,
      "stddev": 0.0017228267297219218,
      "median": 0.0091916788,
      "user": 0.003025046666666665,
      "system": 0.005412860000000001,
      "min": 0.006949899800000001,
      "max": 0.0103368908,
      "times": [
        0.0091916788,
        0.0103368908,
        0.006949899800000001
      ],
      "exit_codes": [
        0,
        0,
        0
      ],
      "parameters": {
        "step": "39"
      }
    },
    {
      "command": "./main < ./data/ladrilho_2_40.txt",
      "mean": 0.009839740133333335,
      "stddev": 0.00142376256288973,
      "median": 0.0100124258,
      "user": 0.003972046666666665,
      "system": 0.004601526666666667,
      "min": 0.008337510800000001,
      "max": 0.0111692838,
      "times": [
        0.008337510800000001,
        0.0100124258,
        0.0111692838
      ],
      "exit_codes": [
        0,
        0,
        0
      ],
      "parameters": {
        "step": "40"
      }
    },
    {
      "command": "./main < ./data/ladrilho_2_41.txt",
      "mean": 0.006339247466666667,
      "stddev": 0.002786152077016855,
      "median": 0.007353948800000001,
      "user": 0.002804379999999999,
      "system": 0.003414860000000001,
      "min": 0.0031879548,
      "max": 0.008475838800000001,
      "times": [
        0.007353948800000001,
        0.008475838800000001,
        0.0031879548
      ],
      "exit_codes": [
        0,
        0,
        0
      ],
      "parameters": {
        "step": "41"
      }
    },
    {
      "command": "./main < ./data/ladrilho_2_42.txt",
      "mean": 0.0018898997999999996,
      "stddev": 0.0010789479787223293,
      "median": 0.0017626068000000002,
      "user": 0.002345713333333332,
      "system": 0.00044724000000000066,
      "min": 0.000880244799999999,
      "max": 0.0030268477999999994,
      "times": [
        0.0017626068000000002,
        0.000880244799999999,
        0.0030268477999999994
      ],
      "exit_codes": [
        0,
        0,
        0
      ],
      "parameters": {
        "step": "42"
      }
    },
    {
      "command": "./main < ./data/ladrilho_2_43.txt",
      "mean": 0.004654539466666667,
      "stddev": 0.0006766970170130309,
      "median": 0.0046181178,
      "user": 0.001767379999999999,
      "system": 0.002906860000000001,
      "min": 0.0039967888,
      "max": 0.005348711800000001,
      "times": [
        0.0046181178,
        0.005348711800000001,
        0.0039967888
      ],
      "exit_codes": [
        0,
        0,
        0
      ],
      "parameters": {
        "step": "43"
      }
    },
    {
      "command": "./main < ./data/ladrilho_2_44.txt",
      "mean": 0.005122220799999999,
      "stddev": 0.0008581380641458569,
      "median": 0.0047429607999999995,
      "user": 0.0028963799999999987,
      "system": 0.0025518600000000013,
      "min": 0.004519056799999999,
      "max": 0.006104644799999998,
      "times": [
        0.004519056799999999,
        0.0047429607999999995,
        0.006104644799999998
      ],
      "exit_codes": [
        0,
        0,
        0
      ],
      "parameters": {
        "step": "44"
      }
    },
    {
      "command": "./main < ./data/ladrilho_2_45.txt",
      "mean": 0.004756992466666667,
      "stddev": 0.000855493169785904,
      "median": 0.0043735088,
      "user": 0.002647046666666665,
      "system": 0.002444526666666668,
      "min": 0.0041603348,
      "max": 0.0057371338000000004,
      "times": [
        0.0057371338000000004,
        0.0041603348,
        0.0043735088
      ],
      "exit_codes": [
        0,
        0,
        0
      ],
      "parameters": {
        "step": "45"
      }
    },
    {
      "command": "./main < ./data/ladrilho_2_46.txt",
      "mean": 0.005575808800000001,
      "stddev": 0.000855675774069244,
      "median": 0.005839293800000001,
      "user": 0.0038353799999999993,
      "system": 0.002010860000000001,
      "min": 0.0046193768,
      "max": 0.006268755799999999,
      "times": [
        0.0046193768,
        0.006268755799999999,
        0.005839293800000001
      ],
      "exit_codes": [
        0,
        0,
        0
      ],
      "parameters": {
        "step": "46"
      }
    },
    {
      "command": "./main < ./data/ladrilho_2_47.txt",
      "mean": 0.006001201799999999,
      "stddev": 0.0017954698018950365,
      "median": 0.0062691178,
      "user": 0.0038740466666666654,
      "system": 0.0023081933333333345,
      "min": 0.004086828799999999,
      "max": 0.0076476588,
      "times": [
        0.0062691178,
        0.0076476588,
        0.004086828799999999
      ],
      "exit_codes": [
        0,
        0,
        0
      ],
      "parameters": {
        "step": "47"
      }
    },
    {
      "command": "./main < ./data/ladrilho_2_48.txt",
      "mean": 0.006522550800000001,
      "stddev": 0.0012503781759399832,
      "median": 0.006389428800000001,
      "user": 0.002497586666666666,
      "system": 0.003670193333333334,
      "min": 0.0053440598,
      "max": 0.0078341638,
      "times": [
        0.0053440598,
        0.0078341638,
        0.006389428800000001
      ],
      "exit_codes": [
        0,
        0,
        0
      ],
      "parameters": {
        "step": "48"
      }
    },
    {
      "command": "./main < ./data/ladrilho_2_49.txt",
      "mean": 0.0066256788,
      "stddev": 0.0013657550160812157,
      "median": 0.0064055078,
      "user": 0.0012095866666666656,
      "system": 0.005172193333333334,
      "min": 0.0053833848,
      "max": 0.008088143800000001,
      "times": [
        0.008088143800000001,
        0.0064055078,
        0.0053833848
      ],
      "exit_codes": [
        0,
        0,
        0
      ],
      "parameters": {
        "step": "49"
      }
    },
    {
      "command": "./main < ./data/ladrilho_2_50.txt",
      "mean": 0.004731912799999999,
      "stddev": 0.0002882925040440702,
      "median": 0.004618628799999998,
      "user": 0.0015719199999999992,
      "system": 0.003722526666666667,
      "min": 0.004517468799999999,
      "max": 0.005059640799999999,
      "times": [
        0.004517468799999999,
        0.004618628799999998,
        0.005059640799999999
      ],
      "exit_codes": [
        0,
        0,
        0
      ],
      "parameters": {
        "step": "50"
      }
    }
  ]
}
